examples/freephonenum_example.py
examples/receivesmss_example.py
examples/sms24me_example.py
examples/waitmsg_example.py
pyvirtualsms/__init__.py
pyvirtualsms/client.py
pyvirtualsms/distributor.py
pyvirtualsms/models.py
pyvirtualsms/providers/freephonenum.py
pyvirtualsms/providers/provider_base.py
pyvirtualsms/providers/receivesmss.py
pyvirtualsms/providers/sms24me.py
pyvirtualsms-0.4.5.dist-info/licenses/LICENSE
pyvirtualsms-0.4.5.dist-info/METADATA
pyvirtualsms-0.4.5.dist-info/WHEEL
pyvirtualsms-0.4.5.dist-info/top_level.txt
pyvirtualsms-0.4.5.dist-info/RECORD
