Metadata-Version: 2.4
Name: pyvirtualsms
Version: 0.4.5
Summary: A lightweight Python library for scraping temporary SMS inboxes from multiple providers.
Author: Ulus
License: MIT License
Project-URL: Homepage, https://github.com/cvcvka5/pyvirtualsms
Project-URL: Source, https://github.com/cvcvka5/pyvirtualsms
Project-URL: Issues, https://github.com/cvcvka5/pyvirtualsms/issues
Requires-Python: >=3.8
License-File: LICENSE
Requires-Dist: requests
Requires-Dist: selectolax
Dynamic: license-file
